MANIFEST.in
setup.py
edubeam/__init__.py
edubeam/__main__.py
edubeam/ebfem.py
edubeam/ebgui.py
edubeam/ebinit.py
edubeam/ebio.py
edubeam/edubeam.py
edubeam/splash.png
edubeam.egg-info/PKG-INFO
edubeam.egg-info/SOURCES.txt
edubeam.egg-info/dependency_links.txt
edubeam.egg-info/requires.txt
edubeam.egg-info/top_level.txt
edubeam/examples/ex01.xml
edubeam/examples/ex02.xml
edubeam/examples/ex03.xml
edubeam/userGuide/EduBeam-userGuide.pdf