Metadata-Version: 1.0
Name: edubeam
Version: 3.5.0
Summary: EduBeam - Linear static analysis of 2D beams
Home-page: http://mech.fsv.cvut.cz/edubeam
Author: Borek Patzak, Jan Stransky, Vit Smilauer
Author-email: info@oofem.org
License: GPL
Platform: UNKNOWN
